AsyncAgentic/__init__.py
AsyncAgentic/Agents/AsyncOpenAISimpleAgent.py
AsyncAgentic/Agents/BaseAgent.py
AsyncAgentic/Agents/__init__.py
AsyncAgentic/DataModels/__init__.py
AsyncAgentic/OpenAIClientBase/AsyncOpenAIBase.py
AsyncAgentic/OpenAIClientBase/__init__.py
asyncagentic-0.1.1.dist-info/METADATA
asyncagentic-0.1.1.dist-info/WHEEL
asyncagentic-0.1.1.dist-info/licenses/LICENSE
asyncagentic-0.1.1.dist-info/RECORD
