Metadata-Version: 2.4
Name: AsyncAgentic
Version: 0.1.1
Summary: Async Agentic Framework For Production Grade Agentic Systems
License-File: LICENSE
Requires-Python: >=3.12.8
Requires-Dist: aiofiles>=24.1.0
Requires-Dist: aiohttp>=3.10.11
Requires-Dist: openai>=1.0.0
Requires-Dist: pybase64>=1.4.1
Requires-Dist: termcolor>=2.4.0
Requires-Dist: tiktoken>=0.7.0
